flask_multipass_ldap_cern.py
Flask_Multipass_LDAP_CERN-2.0.dist-info/METADATA
Flask_Multipass_LDAP_CERN-2.0.dist-info/WHEEL
Flask_Multipass_LDAP_CERN-2.0.dist-info/entry_points.txt
Flask_Multipass_LDAP_CERN-2.0.dist-info/top_level.txt
Flask_Multipass_LDAP_CERN-2.0.dist-info/RECORD
