Metadata-Version: 2.1
Name: Flask-Multipass-LDAP-CERN
Version: 2.0
Summary: CERN-specific Flask-Multipass providers
Home-page: https://github.com/indico/flask-multipass-ldap-cern
Author: Indico Team
Author-email: indico-team@cern.ch
License: BSD
Platform: UNKNOWN
Requires-Dist: flask-multipass
Requires-Dist: python-ldap (<4.0,>=3.3.1)
